setup.py
bin/literate
src/literate.py
src/literate.egg-info/PKG-INFO
src/literate.egg-info/SOURCES.txt
src/literate.egg-info/dependency_links.txt
src/literate.egg-info/top_level.txt