Metadata-Version: 1.1
Name: literate
Version: 0.1.3
Summary: Extracts text and documentation embedded in source code
Home-page: http://github.com/sebastien/literate
Author: Sébastien Pierre
Author-email: sebastien.pierre@gmail.com
License: License :: OSI Approved :: BSD License
Download-URL: https://github.com/sebastien/literate/tarball/0.1.3
Keywords: documentation,programming,tools,literate,markup
Platform: UNKNOWN
Classifier: Programming Language :: Python :: 3
Classifier: Development Status :: 3 - Alpha
Classifier: Natural Language :: English
Classifier: Environment :: Console
Classifier: Intended Audience :: Developers
Classifier: Operating System :: OS Independent
Classifier: Topic :: Utilities
